AlfonsSensor/__init__.py
AlfonsSensor/__main__.py
AlfonsSensor/main.py
AlfonsSensor/sensor.py
AlfonsSensor-0.0.2.dist-info/METADATA
AlfonsSensor-0.0.2.dist-info/RECORD
AlfonsSensor-0.0.2.dist-info/WHEEL
AlfonsSensor-0.0.2.dist-info/entry_points.txt
AlfonsSensor-0.0.2.dist-info/top_level.txt
