Metadata-Version: 2.1
Name: AlfonsSensor
Version: 0.0.2
Summary: A package for sensors to interact with Alfons
Home-page: https://github.com/ntoonio/AlfonsSensor.git
Author: Anton Lindroth
Author-email: ntoonio@gmail.com
License: UNKNOWN
Platform: UNKNOWN
Requires-Dist: AlfonsIoT
